Metadata-Version: 1.0
Name: MAprobabilitydistributionPackage
Version: 0.1
Summary: Gaussian and Binomial distributions
Home-page: UNKNOWN
Author: Maryam A.samani
Author-email: maryam.smni@gmail.com
License: UNKNOWN
Platform: UNKNOWN
